README.rst
setup.py
wishbone_function_template/__init__.py
wishbone_function_template/template.py
wishbone_function_template.egg-info/PKG-INFO
wishbone_function_template.egg-info/SOURCES.txt
wishbone_function_template.egg-info/dependency_links.txt
wishbone_function_template.egg-info/entry_points.txt
wishbone_function_template.egg-info/namespace_packages.txt
wishbone_function_template.egg-info/not-zip-safe
wishbone_function_template.egg-info/requires.txt
wishbone_function_template.egg-info/top_level.txt